emutrader/__init__.py
emutrader/__version__.py
emutrader/api.py
emutrader/constants.py
emutrader/exceptions.py
emutrader/py.typed
emutrader/adapters/__init__.py
emutrader/adapters/base.py
emutrader/adapters/jq_adapter.py
emutrader/adapters/jq_legacy.py
emutrader/adapters/mock_adapter.py
emutrader/adapters/qmt_adapter.py
emutrader/core/__init__.py
emutrader/core/account.py
emutrader/core/context.py
emutrader/core/models.py
emutrader/core/order.py
emutrader/core/portfolio.py
emutrader/core/position.py
emutrader/core/slippage.py
emutrader/core/strategy.py
emutrader/core/subportfolio.py
emutrader/core/trader.py
emutrader/handlers/__init__.py
emutrader/handlers/base.py
emutrader/handlers/credit.py
emutrader/handlers/factory.py
emutrader/handlers/future.py
emutrader/handlers/stock.py
emutrader/storage/__init__.py
emutrader/storage/base.py
emutrader/storage/cache.py
emutrader/storage/memory.py
emutrader/storage/sqlite.py
emutrader/testing/__init__.py
emutrader/testing/mock_data.py
emutrader/testing/test_mode.py
emutrader/testing/test_utils.py
emutrader/utils/__init__.py
emutrader/utils/data.py
emutrader/utils/performance.py
emutrader-0.1.4.dist-info/licenses/LICENSE
emutrader-0.1.4.dist-info/METADATA
emutrader-0.1.4.dist-info/WHEEL
emutrader-0.1.4.dist-info/entry_points.txt
emutrader-0.1.4.dist-info/top_level.txt
emutrader-0.1.4.dist-info/RECORD
