Metadata-Version: 2.4
Name: emutrader
Version: 0.1.4
Summary: A Python library for quantitative trading simulation and backtesting
Home-page: https://gitee.com/xledoo/emutrader
Author: xledoo
Author-email: xledoo <xledoo@gmail.com>
Maintainer-email: xledoo <xledoo@gmail.com>
License: MIT License
Project-URL: Homepage, https://gitee.com/xledoo/emutrader
Project-URL: Documentation, https://emutrader.readthedocs.io/
Project-URL: Repository, https://gitee.com/xledoo/emutrader.git
Project-URL: Bug Tracker, https://gitee.com/xledoo/emutrader/issues
Keywords: quantitative trading,backtesting,simulation,finance,algorithmic trading
Classifier: Development Status :: 3 - Alpha
Classifier: Intended Audience :: Financial and Insurance Industry
Classifier: Intended Audience :: Developers
Classifier: License :: OSI Approved :: MIT License
Classifier: Operating System :: OS Independent
Classifier: Programming Language :: Python :: 3
Classifier: Programming Language :: Python :: 3.8
Classifier: Programming Language :: Python :: 3.9
Classifier: Programming Language :: Python :: 3.10
Classifier: Programming Language :: Python :: 3.11
Classifier: Topic :: Office/Business :: Financial :: Investment
Classifier: Topic :: Scientific/Engineering :: Mathematics
Requires-Python: >=3.8
License-File: LICENSE
Requires-Dist: numpy>=1.21.0
Requires-Dist: pandas>=1.3.0
Requires-Dist: pyyaml>=6.0
Requires-Dist: loguru>=0.6.0
Requires-Dist: typing-extensions>=4.0.0
Provides-Extra: dev
Requires-Dist: pytest>=6.0; extra == "dev"
Requires-Dist: pytest-cov; extra == "dev"
Requires-Dist: black; extra == "dev"
Requires-Dist: flake8; extra == "dev"
Requires-Dist: mypy; extra == "dev"
Requires-Dist: pre-commit; extra == "dev"
Provides-Extra: docs
Requires-Dist: sphinx; extra == "docs"
Requires-Dist: sphinx-rtd-theme; extra == "docs"
Requires-Dist: myst-parser; extra == "docs"
Provides-Extra: analysis
Requires-Dist: matplotlib>=3.5.0; extra == "analysis"
Requires-Dist: scipy>=1.7.0; extra == "analysis"
Dynamic: author
Dynamic: home-page
Dynamic: license-file
Dynamic: requires-python
